odoo8_addon_server_env_magentoerpconnect-8.0.1.0.0-py2.7-nspkg.pth
odoo8_addon_server_env_magentoerpconnect-8.0.1.0.0.dist-info/top_level.txt
odoo8_addon_server_env_magentoerpconnect-8.0.1.0.0.dist-info/WHEEL
odoo8_addon_server_env_magentoerpconnect-8.0.1.0.0.dist-info/RECORD
odoo8_addon_server_env_magentoerpconnect-8.0.1.0.0.dist-info/metadata.json
odoo8_addon_server_env_magentoerpconnect-8.0.1.0.0.dist-info/DESCRIPTION.rst
odoo8_addon_server_env_magentoerpconnect-8.0.1.0.0.dist-info/METADATA
odoo8_addon_server_env_magentoerpconnect-8.0.1.0.0.dist-info/namespace_packages.txt
odoo_addons/server_env_magentoerpconnect/__openerp__.py
odoo_addons/server_env_magentoerpconnect/magento_model.py
odoo_addons/server_env_magentoerpconnect/__init__.py
odoo_addons/server_env_magentoerpconnect/i18n/it.po
odoo_addons/server_env_magentoerpconnect/i18n/es.po
odoo_addons/server_env_magentoerpconnect/i18n/sl.po
odoo_addons/server_env_magentoerpconnect/i18n/nl.po
odoo_addons/server_env_magentoerpconnect/i18n/de.po
odoo_addons/server_env_magentoerpconnect/i18n/fr.po
odoo_addons/server_env_magentoerpconnect/i18n/pt_BR.po
